auth/__init__.py
auth/authorization.py
request_verification-0.1.1.dist-info/DESCRIPTION.rst
request_verification-0.1.1.dist-info/METADATA
request_verification-0.1.1.dist-info/RECORD
request_verification-0.1.1.dist-info/WHEEL
request_verification-0.1.1.dist-info/metadata.json
request_verification-0.1.1.dist-info/top_level.txt
