Metadata-Version: 2.0
Name: request-verification
Version: 0.1.1
Summary: Helper to sign requests for feed service
Home-page: https://github.com/redbubble/feed-service
Author: Globack team
Author-email: paul.david@redbubble.com
License: WTFPL
Platform: UNKNOWN
